bgez/__init__.py
bgez/__main__.py
bgez/asyn/__init__.py
bgez/asyn/deferred.py
bgez/asyn/task.py
bgez/asyn/task_manager.py
bgez/components/__init__.py
bgez/components/launcher.py
bgez/core/__init__.py
bgez/core/callbacks.py
bgez/core/dictable.py
bgez/core/events.py
bgez/core/inputs/__init__.py
bgez/core/inputs/axis_type.py
bgez/core/inputs/button_type.py
bgez/core/inputs/input.py
bgez/core/inputs/keymap.py
bgez/core/logging/__api__.py
bgez/core/logging/__init__.py
bgez/core/logging/log.py
bgez/core/logging/logging_server.py
bgez/core/pyon.py
bgez/core/resource.py
bgez/core/saveable.py
bgez/core/sentinel.py
bgez/core/singleton.py
bgez/core/time/__init__.py
bgez/core/time/clock.py
bgez/core/time/scheduler.py
bgez/core/time/timer.py
bgez/core/toggle.py
bgez/core/uri.py
bgez/core/utils/__init__.py
bgez/core/utils/disposable.py
bgez/core/utils/general.py
bgez/core/utils/live.py
bgez/core/utils/loader.py
bgez/core/utils/proxy.py
bgez/core/utils/state.py
bgez/core/utils/symbol.py
bgez/core/utils/time.py
bgez/core/utils/tracing.py
bgez/game/__api__/__init__.py
bgez/game/__api__/game_logic.py
bgez/game/__api__/scene_manager.py
bgez/game/__api__/window_manager.py
bgez/game/__init__.py
bgez/game/blend_file.py
bgez/game/entity.py
bgez/game/inputs/__init__.py
bgez/game/inputs/bge_inputs.py
bgez/game/inputs/bge_registry.py
bgez/game/process/__init__.py
bgez/game/process/game_process.py
bgez/game/process/logic_process.py
bgez/game/process/render_process.py
bgez/game/types/__init__.py
bgez/game/types/armature_object.py
bgez/game/types/blend_library.py
bgez/game/types/camera_object.py
bgez/game/types/game_object.py
bgez/game/types/scene.py
bgez/game/types/stage.py
bgez/game/types/wrapper.py
bgez/network/__init__.py
bgez/network/channel.py
bgez/network/easysocket.py
bgez/network/multiplexer/__init__.py
bgez/network/multiplexer/subchannel.py
bgez/network/multiplexer/wrappers.py
bgez/network/network_manager.py
bgez/network/tcp/__init__.py
bgez/network/tcp/tcp_channel.py
bgez-0.0.1a0.dist-info/entry_points.txt
bgez-0.0.1a0.dist-info/WHEEL
bgez-0.0.1a0.dist-info/METADATA
bgez-0.0.1a0.dist-info/RECORD
